co_op_translator/__main__.py
co_op_translator/cli/__init__.py
co_op_translator/cli/evaluate.py
co_op_translator/cli/migrate_links.py
co_op_translator/cli/translate.py
co_op_translator/config/base_config.py
co_op_translator/config/constants.py
co_op_translator/config/font_config.py
co_op_translator/config/llm_config/__init__.py
co_op_translator/config/llm_config/azure_openai.py
co_op_translator/config/llm_config/config.py
co_op_translator/config/llm_config/openai.py
co_op_translator/config/llm_config/provider.py
co_op_translator/config/vision_config/__init__.py
co_op_translator/config/vision_config/azure_computer_vision.py
co_op_translator/config/vision_config/config.py
co_op_translator/config/vision_config/provider.py
co_op_translator/core/__init__.py
co_op_translator/core/llm/__init__.py
co_op_translator/core/llm/jupyter_notebook_translator.py
co_op_translator/core/llm/markdown_evaluator.py
co_op_translator/core/llm/markdown_translator.py
co_op_translator/core/llm/providers/azure/__init__.py
co_op_translator/core/llm/providers/azure/markdown_evaluator.py
co_op_translator/core/llm/providers/azure/markdown_translator.py
co_op_translator/core/llm/providers/azure/text_translator.py
co_op_translator/core/llm/providers/openai/__init__.py
co_op_translator/core/llm/providers/openai/markdown_evaluator.py
co_op_translator/core/llm/providers/openai/markdown_translator.py
co_op_translator/core/llm/providers/openai/text_translator.py
co_op_translator/core/llm/rule_based_evaluator.py
co_op_translator/core/llm/text_translator.py
co_op_translator/core/project/__init__.py
co_op_translator/core/project/directory_manager.py
co_op_translator/core/project/language_migrator.py
co_op_translator/core/project/project_evaluator.py
co_op_translator/core/project/project_translator.py
co_op_translator/core/project/translation_manager.py
co_op_translator/core/vision/__init__.py
co_op_translator/core/vision/image_translator.py
co_op_translator/core/vision/providers/azure/__init__.py
co_op_translator-0.16.2.dist-info/METADATA
co_op_translator-0.16.2.dist-info/WHEEL
co_op_translator-0.16.2.dist-info/entry_points.txt
co_op_translator-0.16.2.dist-info/licenses/LICENSE
co_op_translator-0.16.2.dist-info/RECORD
