Metadata-Version: 2.4
Name: co_op_translator
Version: 0.16.2
Summary: Easily automate the translation of your documentation into multiple languages to reach a global audience.
License: MIT
License-File: LICENSE
Keywords: translator,translation,azure,openai,gpt
Author: Minseok Song
Author-email: minseok.song@mssong.com
Maintainer: Minseok Song
Maintainer-email: minseok.song@mssong.com
Requires-Python: >=3.10,<3.13
Classifier: License :: OSI Approved :: MIT License
Classifier: Programming Language :: Python :: 3
Classifier: Programming Language :: Python :: 3.10
Classifier: Programming Language :: Python :: 3.11
Classifier: Programming Language :: Python :: 3.12
Requires-Dist: ai-healthcheck (>=0.1.2,<0.2.0)
Requires-Dist: annotated-types (>=0.7.0,<0.8.0)
Requires-Dist: anyio (>=4.4.0,<5.0.0)
Requires-Dist: appnope (>=0.1.4,<0.2.0)
Requires-Dist: arabic-reshaper (>=3.0.0,<4.0.0)
Requires-Dist: asttokens (>=2.4.1,<3.0.0)
Requires-Dist: az-ai-healthcheck[vision] (>=0.1.7,<0.2.0)
Requires-Dist: azure-ai-vision-imageanalysis (>=1.0.0b2,<2.0.0)
Requires-Dist: azure-cognitiveservices-vision-computervision (>=0.9.0,<0.10.0)
Requires-Dist: azure-common (>=1.1.28,<2.0.0)
Requires-Dist: azure-core (>=1.30.2,<2.0.0)
Requires-Dist: certifi (>=2024.6.2,<2025.0.0)
Requires-Dist: charset-normalizer (>=3.3.2,<4.0.0)
Requires-Dist: click (>=8.1.7,<9.0.0)
Requires-Dist: comm (>=0.2.2,<0.3.0)
Requires-Dist: contourpy (>=1.2.1,<2.0.0)
Requires-Dist: cycler (>=0.12.1,<0.13.0)
Requires-Dist: decorator (>=5.1.1,<6.0.0)
Requires-Dist: distro (>=1.9.0,<2.0.0)
Requires-Dist: executing (>=2.0.1,<3.0.0)
Requires-Dist: fonttools (>=4.53.0,<5.0.0)
Requires-Dist: h11 (>=0.14.0,<0.15.0)
Requires-Dist: httpcore (>=1.0.5,<2.0.0)
Requires-Dist: httpx (>=0.27.0,<0.28.0)
Requires-Dist: idna (>=3.7,<4.0)
Requires-Dist: isodate (>=0.6.1,<0.7.0)
Requires-Dist: jedi (>=0.19.1,<0.20.0)
Requires-Dist: kiwisolver (>=1.4.5,<2.0.0)
Requires-Dist: markdown-it-py (>=3.0.0,<4.0.0)
Requires-Dist: matplotlib (>=3.9.0,<4.0.0)
Requires-Dist: matplotlib-inline (>=0.1.7,<0.2.0)
Requires-Dist: msrest (>=0.7.1,<0.8.0)
Requires-Dist: numpy (>=1.25.2,<2.0.0)
Requires-Dist: oauthlib (>=3.2.2,<4.0.0)
Requires-Dist: openai (>=1.108.2,<2.0.0)
Requires-Dist: opencv-python (>=4.10.0.82,<5.0.0.0)
Requires-Dist: packaging (>=24.1,<25.0)
Requires-Dist: parso (>=0.8.4,<0.9.0)
Requires-Dist: pexpect (>=4.9.0,<5.0.0)
Requires-Dist: pillow (>=10.3.0,<11.0.0)
Requires-Dist: platformdirs (>=4.2.2,<5.0.0)
Requires-Dist: prompt_toolkit (>=3.0.47,<4.0.0)
Requires-Dist: psutil (>=5.9.8,<6.0.0)
Requires-Dist: ptyprocess (>=0.7.0,<0.8.0)
Requires-Dist: pure-eval (>=0.2.2,<0.3.0)
Requires-Dist: pydantic (>=2.7.3,<2.10)
Requires-Dist: pydantic_core (>=2.18.4,<3.0.0)
Requires-Dist: pyparsing (>=3.1.2,<4.0.0)
Requires-Dist: python-bidi (>=0.6.6,<0.7.0)
Requires-Dist: python-dateutil (>=2.9.0.post0,<3.0.0)
Requires-Dist: python-dotenv (>=1.0.1,<2.0.0)
Requires-Dist: pyyaml (>=6.0.2,<7.0.0)
Requires-Dist: pyzmq (>=26.0.3,<27.0.0)
Requires-Dist: requests (>=2.32.3,<3.0.0)
Requires-Dist: requests-oauthlib (>=2.0.0,<3.0.0)
Requires-Dist: semantic_kernel (>=1.8.3,<2.0.0)
Requires-Dist: six (>=1.16.0,<2.0.0)
Requires-Dist: sniffio (>=1.3.1,<2.0.0)
Requires-Dist: stack-data (>=0.6.3,<0.7.0)
Requires-Dist: tiktoken (>=0.7.0,<0.8.0)
Requires-Dist: tornado (>=6.4.1,<7.0.0)
Requires-Dist: tqdm (>=4.66.4,<5.0.0)
Requires-Dist: traitlets (>=5.14.3,<6.0.0)
Requires-Dist: typing_extensions (>=4.12.2,<5.0.0)
Requires-Dist: urllib3 (>=2.2.1,<3.0.0)
Requires-Dist: wcwidth (>=0.2.13,<0.3.0)
Project-URL: Documentation, https://github.com/Azure/co-op-translator/tree/main/getting_started
Project-URL: Repository, https://github.com/Azure/co-op-translator
